setup.py
Allegro.egg-info/PKG-INFO
Allegro.egg-info/SOURCES.txt
Allegro.egg-info/dependency_links.txt
Allegro.egg-info/requires.txt
Allegro.egg-info/top_level.txt
allegro/__init__.py
allegro/app.py
allegro/controller.py