Metadata-Version: 1.1
Name: Allegro
Version: 1.1.5
Summary: A python backend integration framework
Home-page: https://github.com/Alecyrus/Allegro
Author: Alecyrus
Author-email: alecyrus@163.com
License: MIT
Platform: any
Classifier: Development Status :: 2 - Pre-Alpha
Classifier: Environment :: Web Environment
Classifier: License :: OSI Approved :: MIT License
Classifier: Programming Language :: Python :: 3.5
